LICENSE
README.md
omnio/__init__.py
omnio/config.py
omnio/glob.py
omnio/http.py
omnio/lib.py
omnio/path.py
omnio/s3.py
omnio-1.3.0.dist-info/LICENSE
omnio-1.3.0.dist-info/WHEEL
omnio-1.3.0.dist-info/METADATA
omnio-1.3.0.dist-info/RECORD
