Metadata-Version: 2.1
Name: omnio
Version: 1.3.0
Summary: Python library for opening URIs as streaming file-like objects
Home-page: https://github.com/scoutexchange/omnio
License: MIT
Author: Bob Green
Author-email: rgreen@aquent.com
Requires-Python: >=3.7,<4.0
Classifier: Development Status :: 5 - Production/Stable
Classifier: Intended Audience :: Developers
Classifier: License :: OSI Approved :: MIT License
Classifier: Natural Language :: English
Classifier: Operating System :: OS Independent
Classifier: Programming Language :: Python
Classifier: Programming Language :: Python :: 3
Classifier: Programming Language :: Python :: 3.10
Classifier: Programming Language :: Python :: 3.7
Classifier: Programming Language :: Python :: 3.8
Classifier: Programming Language :: Python :: 3.9
Classifier: Topic :: Internet :: WWW/HTTP
Classifier: Topic :: Software Development :: Libraries :: Python Modules
Classifier: Topic :: Utilities
Requires-Dist: boto3 (>=1.10,<2.0)
Requires-Dist: requests (>=2.22,<3.0)
Project-URL: Repository, https://github.com/scoutexchange/omnio
